hipsterplot.py
hipsterplot-0.1.dist-info/DESCRIPTION.rst
hipsterplot-0.1.dist-info/METADATA
hipsterplot-0.1.dist-info/RECORD
hipsterplot-0.1.dist-info/WHEEL
hipsterplot-0.1.dist-info/metadata.json
hipsterplot-0.1.dist-info/top_level.txt
